kitchen3_sdk/__init__.py
kitchen3_sdk/api/__init__.py
kitchen3_sdk/api/default_api.py
kitchen3_sdk/api_client.py
kitchen3_sdk/api_response.py
kitchen3_sdk/configuration.py
kitchen3_sdk/exceptions.py
kitchen3_sdk/models/__init__.py
kitchen3_sdk/models/item.py
kitchen3_sdk/models/query_input.py
kitchen3_sdk/py.typed
kitchen3_sdk/rest.py
kitchen3_sdk-0.0.1.dist-info/METADATA
kitchen3_sdk-0.0.1.dist-info/WHEEL
kitchen3_sdk-0.0.1.dist-info/RECORD
